tilebox/storage/__init__.py
tilebox/storage/aio.py
tilebox/storage/granule.py
tilebox/storage/providers.py
tilebox_storage-0.48.0.dist-info/METADATA
tilebox_storage-0.48.0.dist-info/WHEEL
tilebox_storage-0.48.0.dist-info/RECORD
