Metadata-Version: 2.4
Name: tilebox-storage
Version: 0.48.0
Summary: Storage client for Tilebox
Project-URL: Homepage, https://tilebox.com
Project-URL: Documentation, https://docs.tilebox.com/
Author-email: "Tilebox, Inc." <support@tilebox.com>
License: MIT License
Classifier: Intended Audience :: Developers
Classifier: Intended Audience :: Science/Research
Classifier: License :: OSI Approved :: MIT License
Classifier: Operating System :: OS Independent
Classifier: Programming Language :: Python
Classifier: Programming Language :: Python :: 3
Classifier: Programming Language :: Python :: 3.10
Classifier: Programming Language :: Python :: 3.11
Classifier: Programming Language :: Python :: 3.12
Classifier: Programming Language :: Python :: 3.13
Classifier: Topic :: Scientific/Engineering
Classifier: Topic :: Software Development
Requires-Python: >=3.10
Requires-Dist: aiofile>=3.8
Requires-Dist: boto3>=1.37.0
Requires-Dist: folium>=0.15
Requires-Dist: httpx>=0.27
Requires-Dist: obstore>=0.8.0
Requires-Dist: shapely>=2
Requires-Dist: tilebox-datasets
